headlight/__init__.py
headlight/__main__.py
headlight/console.py
headlight/database.py
headlight/drivers/__init__.py
headlight/drivers/base.py
headlight/drivers/postgresql.py
headlight/exceptions.py
headlight/migrator.py
headlight/schema/__init__.py
headlight/schema/builder.py
headlight/schema/ops.py
headlight/schema/schema.py
headlight/schema/types.py
headlight/utils.py
headlight-0.1.14.dist-info/entry_points.txt
headlight-0.1.14.dist-info/LICENSE
headlight-0.1.14.dist-info/WHEEL
headlight-0.1.14.dist-info/METADATA
headlight-0.1.14.dist-info/RECORD
