Metadata-Version: 2.1
Name: headlight
Version: 0.1.14
Summary: A database migration toolkit.
Home-page: https://github.com/alex-oleshkevich/headlight
License: MIT
Author: Alex Oleshkevich
Author-email: alex.oleshkevich@gmail.com
Requires-Python: >=3.10.0,<4.0.0
Classifier: Development Status :: 5 - Production/Stable
Classifier: Environment :: Web Environment
Classifier: Intended Audience :: Developers
Classifier: License :: OSI Approved :: MIT License
Classifier: Operating System :: OS Independent
Classifier: Programming Language :: Python :: 3
Classifier: Programming Language :: Python :: 3.10
Classifier: Programming Language :: Python :: 3
Classifier: Programming Language :: Python :: 3.10
Classifier: Topic :: Software Development :: Libraries :: Python Modules
Classifier: Typing :: Typed
Provides-Extra: postgresql
Requires-Dist: click (>=8.1.3,<9.0.0)
Requires-Dist: psycopg2-binary (>=2.9.3,<3.0.0); extra == "postgresql"
Requires-Dist: tomlkit (>=0.11.1,<0.12.0)
Project-URL: Documentation, https://github.com/alex-oleshkevich/headlight
Project-URL: Repository, https://github.com/alex-oleshkevich/headlight
